{"codigo":"76061110","ex":"","tipo":"0","descricao":"Com um teor, em peso, de silício superior ou igual a 0,05% e inferior ou igual a 0,20%, de ferro superior ou igual a 0,20% e inferior ou igual a 0,40%, de cobre inferior ou igual a 0,05%, de zinco inferior ou igual a 0,05%, de manganês inferior ou igual a","nacionalfederal":"16.45","importadosfederal":"18.29","estadual":"0.00","municipal":"0.00","vigenciainicio":"2015-01-01","vigenciafim":"2015-06-30","chave":"9oi3aC","versao":"15.1.C","fonte":"IBPT"}